tax/__init__.py
tax/__main__.py
tax/session.py
tax-1.0.0.dist-info/DESCRIPTION.rst
tax-1.0.0.dist-info/METADATA
tax-1.0.0.dist-info/RECORD
tax-1.0.0.dist-info/WHEEL
tax-1.0.0.dist-info/entry_points.txt
tax-1.0.0.dist-info/metadata.json
tax-1.0.0.dist-info/top_level.txt
